mbox_exporter/__init__.py
mbox_tools/__init__.py
mbox_tools-0.3.0.dist-info/DESCRIPTION.rst
mbox_tools-0.3.0.dist-info/METADATA
mbox_tools-0.3.0.dist-info/RECORD
mbox_tools-0.3.0.dist-info/WHEEL
mbox_tools-0.3.0.dist-info/metadata.json
mbox_tools-0.3.0.dist-info/top_level.txt
