Metadata-Version: 2.0
Name: mbox-tools
Version: 0.3.0
Summary: Simple tools for summarizing .mbox email archives.
Home-page: https://github.com/DallasMorningNews/mbox-tools/
Author: Allan James Vestal, The Dallas Morning News
Author-email: newsapps@dallasnews.com
License: AGPLv3
Download-URL: https://github.com/DallasMorningNews/mbox-tools/archive/0.3.0.tar.gz
Platform: UNKNOWN
Classifier: Development Status :: 3 - Alpha
Classifier: Intended Audience :: Developers
Classifier: License :: OSI Approved :: GNU Affero General Public License v3
Classifier: Operating System :: OS Independent
Classifier: Programming Language :: Python
Classifier: Programming Language :: Python :: 3
Classifier: Programming Language :: Python :: 3.5
Classifier: Programming Language :: Python :: 3.6
Classifier: Topic :: Communications :: Email
Requires-Dist: mailbox (~=0.4)
